pytest_infrahouse/__init__.py
pytest_infrahouse/plugin.py
pytest_infrahouse/terraform.py
pytest_infrahouse/utils.py
pytest_infrahouse/data/elasticsearch/.gitignore
pytest_infrahouse/data/elasticsearch/datasources.tf
pytest_infrahouse/data/elasticsearch/keypair.tf
pytest_infrahouse/data/elasticsearch/main.tf
pytest_infrahouse/data/elasticsearch/outputs.tf
pytest_infrahouse/data/elasticsearch/providers.tf
pytest_infrahouse/data/elasticsearch/terraform.tf
pytest_infrahouse/data/elasticsearch/variables.tf
pytest_infrahouse/data/instance-profile/data_sources.tf
pytest_infrahouse/data/instance-profile/main.tf
pytest_infrahouse/data/instance-profile/outputs.tf
pytest_infrahouse/data/instance-profile/providers.tf
pytest_infrahouse/data/instance-profile/terraform.tf
pytest_infrahouse/data/instance-profile/variables.tf
pytest_infrahouse/data/jumphost/datasources.tf
pytest_infrahouse/data/jumphost/keypair.tf
pytest_infrahouse/data/jumphost/main.tf
pytest_infrahouse/data/jumphost/outputs.tf
pytest_infrahouse/data/jumphost/providers.tf
pytest_infrahouse/data/jumphost/terraform.tf
pytest_infrahouse/data/jumphost/variables.tf
pytest_infrahouse/data/postgres/main.tf
pytest_infrahouse/data/postgres/outputs.tf
pytest_infrahouse/data/postgres/providers.tf
pytest_infrahouse/data/postgres/terraform.tf
pytest_infrahouse/data/postgres/variables.tf
pytest_infrahouse/data/probe-role/data_sources.tf
pytest_infrahouse/data/probe-role/main.tf
pytest_infrahouse/data/probe-role/outputs.tf
pytest_infrahouse/data/probe-role/providers.tf
pytest_infrahouse/data/probe-role/terraform.tf
pytest_infrahouse/data/probe-role/variables.tf
pytest_infrahouse/data/service-network/datasources.tf
pytest_infrahouse/data/service-network/main.tf
pytest_infrahouse/data/service-network/outputs.tf
pytest_infrahouse/data/service-network/providers.tf
pytest_infrahouse/data/service-network/terraform.tf
pytest_infrahouse/data/service-network/variables.tf
pytest_infrahouse/data/ses/datasources.tf
pytest_infrahouse-0.24.0.dist-info/licenses/LICENSE
pytest_infrahouse-0.24.0.dist-info/METADATA
pytest_infrahouse-0.24.0.dist-info/WHEEL
pytest_infrahouse-0.24.0.dist-info/entry_points.txt
pytest_infrahouse-0.24.0.dist-info/top_level.txt
pytest_infrahouse-0.24.0.dist-info/RECORD
