Metadata-Version: 2.4
Name: pytest-infrahouse
Version: 0.24.0
Summary: A set of fixtures to use with pytest
Author-email: Oleksandr Kuzminskyi <aleks@infrahouse.com>
Maintainer-email: Oleksandr Kuzminskyi <aleks@infrahouse.com>
License: 
Project-URL: Repository, https://github.com/infrahouse/pytest-infrahouse
Classifier: Framework :: Pytest
Classifier: Development Status :: 4 - Beta
Classifier: Intended Audience :: Developers
Classifier: Topic :: Software Development :: Testing
Classifier: Operating System :: OS Independent
Classifier: Programming Language :: Python
Classifier: Programming Language :: Python :: 3.10
Classifier: Programming Language :: Python :: 3.11
Classifier: Programming Language :: Python :: 3.12
Classifier: Programming Language :: Python :: 3.13
Classifier: Programming Language :: Python :: 3 :: Only
Classifier: Programming Language :: Python :: Implementation :: CPython
Classifier: Programming Language :: Python :: Implementation :: PyPy
Classifier: License :: OSI Approved :: Apache Software License
Requires-Python: >=3.8
License-File: LICENSE
Requires-Dist: PyYAML~=6.0
Requires-Dist: black~=25.0
Requires-Dist: boto3~=1.35
Requires-Dist: botocore~=1.35
Requires-Dist: build~=1.2
Requires-Dist: bump2version~=1.0
Requires-Dist: isort~=7.0
Requires-Dist: pytest~=9.0
Requires-Dist: requests~=2.32
Dynamic: license-file
